mkite_conformer/recipes/__init__.py
mkite_conformer/recipes/rdkit.py
mkite_conformer/recipes/tests/__init__.py
mkite_conformer/recipes/tests/test_rdkit.py
mkite_conformer/runners/__init__.py
mkite_conformer/runners/rdkit.py
mkite_conformer/runners/tests/__init__.py
mkite_conformer/runners/tests/test_rdkit.py
mkite_conformer/tests/__init__.py
mkite_conformer/tests/files/__init__.py
mkite_conformer/tests/files/molecule.json
mkite_conformer/tests/files/tea.sdf
mkite_conformer-25.11.3.dist-info/licenses/LICENSE
mkite_conformer-25.11.3.dist-info/licenses/NOTICE
mkite_conformer-25.11.3.dist-info/METADATA
mkite_conformer-25.11.3.dist-info/WHEEL
mkite_conformer-25.11.3.dist-info/entry_points.txt
mkite_conformer-25.11.3.dist-info/top_level.txt
mkite_conformer-25.11.3.dist-info/RECORD
