Metadata-Version: 2.4
Name: mkite_conformer
Version: 25.11.3
Summary: plugin to deal with conformer generation in mkite
Author-email: Daniel Schwalbe-Koda <dskoda@ucla.edu>
Keywords: workflow,materials-science,chemistry
Requires-Python: >=3.8
License-File: LICENSE
License-File: NOTICE
Requires-Dist: mkite_core
Requires-Dist: rdkit
Dynamic: license-file
